{
  "project_info": {
    "project_number": "618641251660",
    "firebase_url": "https://arcall-default-rtdb.europe-west1.firebasedatabase.app",
    "project_id": "arcall",
    "storage_bucket": "arcall.appspot.com"
  },
  "client": [
    {
      "client_info": {
        "mobilesdk_app_id": "1:618641251660:android:340d1e9cc6b2d8bd65c3e9",
        "android_client_info": {
          "package_name": "com.skrl.ARCall"
        }
      },
      "oauth_client": [
        {
          "client_id": "618641251660-pco8585kh4rdhvht0b9gabasdhfdegnl.apps.googleusercontent.com",
          "client_type": 3
        }
      ],
      "api_key": [
        {
          "current_key": "AIzaSyDk_0eoqdsVdv4jQX-lUHLb0Myvshnv_Vo"
        }
      ],
      "services": {
        "appinvite_service": {
          "other_platform_oauth_client": [
            {
              "client_id": "618641251660-pco8585kh4rdhvht0b9gabasdhfdegnl.apps.googleusercontent.com",
              "client_type": 3
            }
          ]
        }
      }
    }
  ],
  "configuration_version": "1"
}